[
    {
        "id": 1,
        "tenthongso": "Coliform (CFU/100 mL)",
        "donvitinh": "CFU/100 mL",
        "gioihan_toithieu": 0.0,
        "gioihan_toida": 3.0,
        "batbuoc":1
    },
    {
        "id": 2,
        "tenthongso": "E.Coli hoặc Coliform chịu nhiệt",
        "donvitinh": "CFU/100 mL",
        "gioihan_toithieu": 0.0,
        "gioihan_toida": 1.0,
        "batbuoc":1
    },
    {
        "id": 3,
        "tenthongso": "Arsenic (As)(*)",
        "donvitinh": "mg/L",
        "gioihan_toithieu": 0,
        "gioihan_toida": 0.01,
        "batbuoc":1
    },
    {
        "id": 4,
        "tenthongso": "Clo dư tự do (**)",
        "donvitinh": "mg/L",
        "gioihan_toithieu": 0.2,
        "gioihan_toida": 1.0,
        "batbuoc":1
    },
    {
        "id": 5,
        "tenthongso": "Độ đục",
        "donvitinh": "NTU",
        "gioihan_toithieu": 0,
        "gioihan_toida": 2.0,
        "batbuoc":1
    },
    {
        "id": 6,
        "tenthongso": "Màu sắc",
        "donvitinh": "TCU",
        "gioihan_toithieu": 0,
        "gioihan_toida": 15,
        "batbuoc":1
    },
    {
        "id": 7,
        "tenthongso": "Mùi, vị",
        "donvitinh": "-",
        "gioihan_toithieu": 0.0,
        "gioihan_toida": 0.0,
        "batbuoc":1
    },
    {
        "id": 8,
        "tenthongso": "pH",
        "donvitinh": "-",
        "gioihan_toithieu": 6.0,
        "gioihan_toida": 8.5,
        "batbuoc":1
        
    },
    {
        "id": 9,
        "tenthongso": "Tụ cầu vàng (Staphylococcus aureus)",
        "donvitinh": "CFU/ 100mL",
        "gioihan_toithieu": 0.0,
        "gioihan_toida": 1.0,
        "batbuoc":0
        
    },
    {
        "id": 10,
        "tenthongso": "Trực khuẩn mủ xanh (Ps. Aeruginosa)",
        "donvitinh": "CFU/ 100mL",
        "gioihan_toithieu": 0.0,
        "gioihan_toida": 1.0,
        "batbuoc":0
        
    },
    {
        "id": 11,
        "tenthongso": "Amoni (NH3 và NH4+ tính theo N)",
        "donvitinh": "mg/L",
        "gioihan_toithieu": 0,
        "gioihan_toida": 0.30000000000000004,
        "batbuoc":0
        
    },
    {
        "id": 12,
        "tenthongso": "Antimon (Sb)",
        "donvitinh": "mg/L",
        "gioihan_toithieu": 0,
        "gioihan_toida": 0.02,
        "batbuoc":0
        
    },
    {
        "id": 13,
        "tenthongso": "Bari (Bs)",
        "donvitinh": "mg/L",
        "gioihan_toithieu": 0,
        "gioihan_toida": 0.7,
        "batbuoc":0
        
    },
    {
        "id": 14,
        "tenthongso": "Bor tính chung cho cả Borat và axit Boric (B)",
        "donvitinh": "mg/L",
        "gioihan_toithieu": 0,
        "gioihan_toida": 0.30000000000000004,
        "batbuoc":0
        
    },
    {
        "id": 15,
        "tenthongso": "Cadmi (Cd)",
        "donvitinh": "mg/L",
        "gioihan_toithieu": 0,
        "gioihan_toida": 0.003,
        "batbuoc":0
        
    },
    {
        "id": 16,
        "tenthongso": "Chì (Plumbum) (Pb)",
        "donvitinh": "mg/L",
        "gioihan_toithieu": 0,
        "gioihan_toida": 0.01,
        "batbuoc":0
        
    },
    {
        "id": 17,
        "tenthongso": "Chỉ số pecmanganat",
        "donvitinh": "mg/L",
        "gioihan_toithieu": 0,
        "gioihan_toida": 2.0,
        "batbuoc":0
        
    },
    {
        "id": 18,
        "tenthongso": "Chloride (Cl-)(***)",
        "donvitinh": "mg/L",
        "gioihan_toithieu": 0,
        "gioihan_toida": 300.0,
        "batbuoc":0
        
    },
    {
        "id": 19,
        "tenthongso": "Chromi (Cr)",
        "donvitinh": "mg/L",
        "gioihan_toithieu": 0,
        "gioihan_toida": 0.05,
        "batbuoc":0
        
    },
    {
        "id": 20,
        "tenthongso": "Đồng (Cuprum) (Cu)",
        "donvitinh": "mg/L",
        "gioihan_toithieu": 0,
        "gioihan_toida": 1.0,
        "batbuoc":0
        
    },
    {
        "id": 21,
        "tenthongso": "Độ cứng, tính theo CaCO3",
        "donvitinh": "mg/L",
        "gioihan_toithieu": 0,
        "gioihan_toida": 300.0,
        "batbuoc":0
        
    },
    {
        "id": 22,
        "tenthongso": "Fluor (F)",
        "donvitinh": "mg/L",
        "gioihan_toithieu": 0,
        "gioihan_toida": 1.5,
        "batbuoc":0
        
    },
    {
        "id": 23,
        "tenthongso": "Kẽm (Zincum) (Zn)",
        "donvitinh": "mg/L",
        "gioihan_toithieu": 0,
        "gioihan_toida": 2.0,
        "batbuoc":0
        
    },
    {
        "id": 24,
        "tenthongso": "Mangan (Mn)",
        "donvitinh": "mg/L",
        "gioihan_toithieu": 0,
        "gioihan_toida": 0.1,
        "batbuoc":0
        
    },
    {
        "id": 25,
        "tenthongso": "Natri (Na)",
        "donvitinh": "mg/L",
        "gioihan_toithieu": 0,
        "gioihan_toida": 200.0,
        "batbuoc":0
        
    },
    {
        "id": 26,
        "tenthongso": "Nhôm (Aluminium) (Al)",
        "donvitinh": "mg/L",
        "gioihan_toithieu": 0,
        "gioihan_toida": 0.2,
        "batbuoc":0
        
    },
    {
        "id": 27,
        "tenthongso": "Nickel (Ni)",
        "donvitinh": "mg/L",
        "gioihan_toithieu": 0,
        "gioihan_toida": 0.07,
        "batbuoc":0
        
    },
    {
        "id": 28,
        "tenthongso": "Nitrat (NO3- tính theo N)",
        "donvitinh": "mg/L",
        "gioihan_toithieu": 0,
        "gioihan_toida": 2.0,
        "batbuoc":0
        
    },
    {
        "id": 29,
        "tenthongso": "Nitrit (NO2- tính theo N) ",
        "donvitinh": "mg/L",
        "gioihan_toithieu": 0,
        "gioihan_toida": 0.05,
        "batbuoc":0
        
    },
    {
        "id": 30,
        "tenthongso": "Sắt (Ferrum) (Fe)",
        "donvitinh": "mg/L",
        "gioihan_toithieu": 0,
        "gioihan_toida": 0.30000000000000004,
        "batbuoc":0
        
    },
    {
        "id": 31,
        "tenthongso": "Seleni (Se)",
        "donvitinh": "mg/L",
        "gioihan_toithieu": 0,
        "gioihan_toida": 0.01,
        "batbuoc":0
        
    },
    {
        "id": 32,
        "tenthongso": "Sunphat",
        "donvitinh": "mg/L",
        "gioihan_toithieu": 0,
        "gioihan_toida": 250.0,
        "batbuoc":0
        
    },
    {
        "id": 33,
        "tenthongso": "Sunfua",
        "donvitinh": "mg/L",
        "gioihan_toithieu": 0,
        "gioihan_toida": 0.05,
        "batbuoc":0
        
    },
    {
        "id": 34,
        "tenthongso": "Thuỷ ngân (Hydrargyrum) (Hg)",
        "donvitinh": "mg/L",
        "gioihan_toithieu": 0,
        "gioihan_toida": 0.001,
        "batbuoc":0
        
    },
    {
        "id": 35,
        "tenthongso": "Tổng chất rắn hoà tan (TDS)",
        "donvitinh": "mg/L",
        "gioihan_toithieu": 0,
        "gioihan_toida": 1000.0,
        "batbuoc":0
        
    },
    {
        "id": 36,
        "tenthongso": "Xyanua (CN-)",
        "donvitinh": "mg/L",
        "gioihan_toithieu": 0,
        "gioihan_toida": 0.05,
        "batbuoc":0
        
    },
    {
        "id": 37,
        "tenthongso": "1,1,1 - Tricloroetan",
        "donvitinh": "μg/L",
        "gioihan_toithieu": 0,
        "gioihan_toida": 2000.0,
        "batbuoc":0
        
    },
    {
        "id": 38,
        "tenthongso": "1,2 - Dicloroetan",
        "donvitinh": "μg/L",
        "gioihan_toithieu": 0,
        "gioihan_toida": 30.0,
        "batbuoc":0
        
    },
    {
        "id": 39,
        "tenthongso": "1,2 - Dicloroeten",
        "donvitinh": "μg/L",
        "gioihan_toithieu": 0,
        "gioihan_toida": 50.0,
        "batbuoc":0
        
    },
    {
        "id": 40,
        "tenthongso": "Cacbontetraclorua",
        "donvitinh": "μg/L",
        "gioihan_toithieu": 0,
        "gioihan_toida": 2.0,
        "batbuoc":0
        
    },
    {
        "id": 41,
        "tenthongso": "Diclorometan",
        "donvitinh": "μg/L",
        "gioihan_toithieu": 0,
        "gioihan_toida": 20.0,
        "batbuoc":0
        
    },
    {
        "id": 42,
        "tenthongso": "Tetracloroeten",
        "donvitinh": "μg/L",
        "gioihan_toithieu": 0,
        "gioihan_toida": 40.0,
        "batbuoc":0
        
    },
    {
        "id": 43,
        "tenthongso": "Tricloroeten",
        "donvitinh": "μg/L",
        "gioihan_toithieu": 0,
        "gioihan_toida": 20.0,
        "batbuoc":0
        
    },
    {
        "id": 44,
        "tenthongso": "Vinyl clorua",
        "donvitinh": "μg/L",
        "gioihan_toithieu": 0,
        "gioihan_toida": 0.30000000000000004,
        "batbuoc":0
        
    },
    {
        "id": 45,
        "tenthongso": "Benzen",
        "donvitinh": "μg/L",
        "gioihan_toithieu": 0,
        "gioihan_toida": 10.0,
        "batbuoc":0
        
    },
    {
        "id": 46,
        "tenthongso": "Etylbenzen",
        "donvitinh": "μg/L",
        "gioihan_toithieu": 0,
        "gioihan_toida": 300.0,
        "batbuoc":0
        
    },
    {
        "id": 47,
        "tenthongso": "Phenol và dẫn xuất của Phenol",
        "donvitinh": "μg/L",
        "gioihan_toithieu": 0,
        "gioihan_toida": 1.0,
        "batbuoc":0
        
    },
    {
        "id": 48,
        "tenthongso": "Styren",
        "donvitinh": "μg/L",
        "gioihan_toithieu": 0,
        "gioihan_toida": 20.0,
        "batbuoc":0
        
    },
    {
        "id": 49,
        "tenthongso": "Toluen ",
        "donvitinh": "μg/L",
        "gioihan_toithieu": 0,
        "gioihan_toida": 700.0,
        "batbuoc":0
        
    },
    {
        "id": 50,
        "tenthongso": "Xylen ",
        "donvitinh": "μg/L",
        "gioihan_toithieu": 0,
        "gioihan_toida": 500.0,
        "batbuoc":0
        
    },
    {
        "id": 51,
        "tenthongso": "1,2 - Diclorobenzen",
        "donvitinh": "μg/L",
        "gioihan_toithieu": 0,
        "gioihan_toida": 1000.0,
        "batbuoc":0
        
    },
    {
        "id": 52,
        "tenthongso": "Monoclorobenzen",
        "donvitinh": "μg/L",
        "gioihan_toithieu": 0,
        "gioihan_toida": 300.0,
        "batbuoc":0
        
    },
    {
        "id": 53,
        "tenthongso": "Triclorobenzen ",
        "donvitinh": "μg/L",
        "gioihan_toithieu": 0,
        "gioihan_toida": 20.0,
        "batbuoc":0
        
    },
    {
        "id": 54,
        "tenthongso": "Acrylamide",
        "donvitinh": "μg/L",
        "gioihan_toithieu": 0,
        "gioihan_toida": 0.5,
        "batbuoc":0
        
    },
    {
        "id": 55,
        "tenthongso": "Epiclohydrin",
        "donvitinh": "μg/L",
        "gioihan_toithieu": 0,
        "gioihan_toida": 0.4,
        "batbuoc":0
        
    },
    {
        "id": 56,
        "tenthongso": "Hexacloro butadien",
        "donvitinh": "μg/L",
        "gioihan_toithieu": 0,
        "gioihan_toida": 0.6000000000000001,
        "batbuoc":0
        
    },
    {
        "id": 57,
        "tenthongso": "1,2 - Dibromo - 3 Cloropropan",
        "donvitinh": "μg/L",
        "gioihan_toithieu": 0,
        "gioihan_toida": 1.0,
        "batbuoc":0
        
    },
    {
        "id": 58,
        "tenthongso": "1,2 -  Dicloropropan",
        "donvitinh": "μg/L",
        "gioihan_toithieu": 0,
        "gioihan_toida": 40.0,
        "batbuoc":0
        
    },
    {
        "id": 59,
        "tenthongso": "1,3 -  Dichloropropen",
        "donvitinh": "μg/L",
        "gioihan_toithieu": 0,
        "gioihan_toida": 20.0,
        "batbuoc":0
        
    },
    {
        "id": 60,
        "tenthongso": "2,4 – D",
        "donvitinh": "μg/L",
        "gioihan_toithieu": 0,
        "gioihan_toida": 30.0,
        "batbuoc":0
        
    },
    {
        "id": 61,
        "tenthongso": "2,4 - DB",
        "donvitinh": "μg/L",
        "gioihan_toithieu": 0,
        "gioihan_toida": 90.0,
        "batbuoc":0
        
    },
    {
        "id": 62,
        "tenthongso": "Alachlor",
        "donvitinh": "μg/L",
        "gioihan_toithieu": 0,
        "gioihan_toida": 20.0,
        "batbuoc":0
        
    },
    {
        "id": 63,
        "tenthongso": "Aldicarb",
        "donvitinh": "μg/L",
        "gioihan_toithieu": 0,
        "gioihan_toida": 10.0,
        "batbuoc":0
        
    },
    {
        "id": 64,
        "tenthongso": "Atrazine và các dẫn xuất chloro-s-triazine",
        "donvitinh": "μg/L",
        "gioihan_toithieu": 0,
        "gioihan_toida": 100.0,
        "batbuoc":0
        
    },
    {
        "id": 65,
        "tenthongso": "Carbofuran",
        "donvitinh": "μg/L",
        "gioihan_toithieu": 0,
        "gioihan_toida": 5.0,
        "batbuoc":0
        
    },
    {
        "id": 66,
        "tenthongso": "Chlorpyrifos",
        "donvitinh": "μg/L",
        "gioihan_toithieu": 0,
        "gioihan_toida": 30.0,
        "batbuoc":0
        
    },
    {
        "id": 67,
        "tenthongso": "Clodane",
        "donvitinh": "μg/L",
        "gioihan_toithieu": 0,
        "gioihan_toida": 0.2,
        "batbuoc":0
        
    },
    {
        "id": 68,
        "tenthongso": "Clorotoluron",
        "donvitinh": "μg/L",
        "gioihan_toithieu": 0,
        "gioihan_toida": 30.0,
        "batbuoc":0
        
    },
    {
        "id": 69,
        "tenthongso": "Cyanazine",
        "donvitinh": "μg/L",
        "gioihan_toithieu": 0,
        "gioihan_toida": 0.6000000000000001,
        "batbuoc":0
        
    },
    {
        "id": 70,
        "tenthongso": "DDT và các dẫn xuất",
        "donvitinh": "μg/L",
        "gioihan_toithieu": 0,
        "gioihan_toida": 1.0,
        "batbuoc":0
        
    },
    {
        "id": 71,
        "tenthongso": "Dichloprop",
        "donvitinh": "μg/L",
        "gioihan_toithieu": 0,
        "gioihan_toida": 100.0,
        "batbuoc":0
        
    },
    {
        "id": 72,
        "tenthongso": "Fenoprop",
        "donvitinh": "μg/L",
        "gioihan_toithieu": 0,
        "gioihan_toida": 9.0,
        "batbuoc":0
        
    },
    {
        "id": 73,
        "tenthongso": "Hydroxyatrazine",
        "donvitinh": "μg/L",
        "gioihan_toithieu": 0,
        "gioihan_toida": 200.0,
        "batbuoc":0
        
    },
    {
        "id": 74,
        "tenthongso": "Isoproturon",
        "donvitinh": "μg/L",
        "gioihan_toithieu": 0,
        "gioihan_toida": 9.0,
        "batbuoc":0
        
    },
    {
        "id": 75,
        "tenthongso": "MCPA",
        "donvitinh": "μg/L",
        "gioihan_toithieu": 0,
        "gioihan_toida": 2.0,
        "batbuoc":0
        
    },
    {
        "id": 76,
        "tenthongso": "Mecoprop",
        "donvitinh": "μg/L",
        "gioihan_toithieu": 0,
        "gioihan_toida": 10.0,
        "batbuoc":0
        
    },
    {
        "id": 77,
        "tenthongso": "Methoxychlor",
        "donvitinh": "μg/L",
        "gioihan_toithieu": 0,
        "gioihan_toida": 20.0,
        "batbuoc":0
        
    },
    {
        "id": 78,
        "tenthongso": "Molinate",
        "donvitinh": "μg/L",
        "gioihan_toithieu": 0,
        "gioihan_toida": 6.0,
        "batbuoc":0
        
    },
    {
        "id": 79,
        "tenthongso": "Pendimetalin",
        "donvitinh": "μg/L",
        "gioihan_toithieu": 0,
        "gioihan_toida": 20.0,
        "batbuoc":0
        
    },
    {
        "id": 80,
        "tenthongso": "Permethrin",
        "donvitinh": "μg/L",
        "gioihan_toithieu": 0,
        "gioihan_toida": 20.0,
        "batbuoc":0
        
    },
    {
        "id": 81,
        "tenthongso": "Propanil",
        "donvitinh": "μg/L",
        "gioihan_toithieu": 0,
        "gioihan_toida": 20.0,
        "batbuoc":0
        
    },
    {
        "id": 82,
        "tenthongso": "Simazine",
        "donvitinh": "μg/L",
        "gioihan_toithieu": 0,
        "gioihan_toida": 2.0,
        "batbuoc":0
        
    },
    {
        "id": 83,
        "tenthongso": "Trifuralin",
        "donvitinh": "μg/L",
        "gioihan_toithieu": 0,
        "gioihan_toida": 20.0,
        "batbuoc":0
        
    },
    {
        "id": 84,
        "tenthongso": "2,4,6 - Triclorophenol",
        "donvitinh": "μg/L",
        "gioihan_toithieu": 0,
        "gioihan_toida": 200.0,
        "batbuoc":0
        
    },
    {
        "id": 85,
        "tenthongso": "Bromat",
        "donvitinh": "μg/L",
        "gioihan_toithieu": 0,
        "gioihan_toida": 10.0,
        "batbuoc":0
        
    },
    {
        "id": 86,
        "tenthongso": "Bromodichloromethane",
        "donvitinh": "μg/L",
        "gioihan_toithieu": 0,
        "gioihan_toida": 60.0,
        "batbuoc":0
        
    },
    {
        "id": 87,
        "tenthongso": "Bromoform",
        "donvitinh": "μg/L",
        "gioihan_toithieu": 0,
        "gioihan_toida": 100.0,
        "batbuoc":0
        
    },
    {
        "id": 88,
        "tenthongso": "Chloroform",
        "donvitinh": "μg/L",
        "gioihan_toithieu": 0,
        "gioihan_toida": 300,
        "batbuoc":0
        
    },
    {
        "id": 89,
        "tenthongso": "Dibromoacetonitrile",
        "donvitinh": "μg/L",
        "gioihan_toithieu": 0,
        "gioihan_toida": 70.0,
        "batbuoc":0
        
    },
    {
        "id": 90,
        "tenthongso": "Dibromochloromethane",
        "donvitinh": "μg/L",
        "gioihan_toithieu": 0,
        "gioihan_toida": 100.0,
        "batbuoc":0
        
    },
    {
        "id": 91,
        "tenthongso": "Dichloroacetonitrile",
        "donvitinh": "μg/L",
        "gioihan_toithieu": 0,
        "gioihan_toida": 20.0,
        "batbuoc":0
        
    },
    {
        "id": 92,
        "tenthongso": "Dichloroacetic acid",
        "donvitinh": "μg/L",
        "gioihan_toithieu": 0,
        "gioihan_toida": 50.0,
        "batbuoc":0
        
    },
    {
        "id": 93,
        "tenthongso": "Formaldehyde",
        "donvitinh": "μg/L",
        "gioihan_toithieu": 0,
        "gioihan_toida": 900.0,
        "batbuoc":0
        
    },
    {
        "id": 94,
        "tenthongso": "Monochloramine",
        "donvitinh": "mg/L",
        "gioihan_toithieu": 0,
        "gioihan_toida": 3.0,
        "batbuoc":0
        
    },
    {
        "id": 95,
        "tenthongso": "Monochloroacetic acid ",
        "donvitinh": "μg/L",
        "gioihan_toithieu": 0,
        "gioihan_toida": 20.0,
        "batbuoc":0
        
    },
    {
        "id": 96,
        "tenthongso": "Trichloroacetic acid ",
        "donvitinh": "μg/L",
        "gioihan_toithieu": 0,
        "gioihan_toida": 200.0,
        "batbuoc":0
        
    },
    {
        "id": 97,
        "tenthongso": "Trichloroaxetonitril",
        "donvitinh": "μg/L",
        "gioihan_toithieu": 0,
        "gioihan_toida": 1.0,
        "batbuoc":0
        
    },
    {
        "id": 98,
        "tenthongso": "Tổng hoạt độ phóng xạ α",
        "donvitinh": "Bq/L",
        "gioihan_toithieu": 0,
        "gioihan_toida": 0.1,
        "batbuoc":0
        
    },
    {
        "id": 99,
        "tenthongso": "Tổng hoạt độ phóng xạ β",
        "donvitinh": "Bq/L",
        "gioihan_toithieu": 0,
        "gioihan_toida": 1.0,
        "batbuoc":0
        
    }
]