{
    "tinhthanh": {
        "type": "dict"
    },
    "xaphuong": {
        "type": "dict"
    },
    "created_by": {
        "type": "string"
    },
    "quanhuyen_id": {
        "type": "string"
    },
    "trangthai_tinhpheduyen": {
        "type": "number"
    },
    "itemhuyen": {
        "type": "list"
    },
    "itemthon": {
        "type": "list"
    },
    "itemxa": {
        "type": "list"
    },
    "created_at": {
        "type": "datetime"
    },
    "vihema_chapthuan": {
        "type": "number"
    },
    "ngay_pheduyet": {
        "type": "datetime"
    },
    "deleted_by": {
        "type": "string"
    },
    "updated_by": {
        "type": "string"
    },
    "tinhthanh_id": {
        "type": "string"
    },
    "itemtinh": {
        "type": "list"
    },
    "deleted": {
        "type": "boolean"
    },
    "id": {
        "primary": true,
        "type": "string"
    },
    "quanhuyen": {
        "type": "dict"
    },
    "xaydungduthao_bcc": {
        "type": "number"
    },
    "nganh": {
        "type": "number"
    },
    "sohoatdong_bcc": {
        "length": null,
        "type": "string"
    },
    "tinhpheduyet_bcc": {
        "length": null,
        "type": "string"
    },
    "deleted_at": {
        "type": "datetime"
    },
    "xaphuong_id": {
        "type": "string"
    },
    "updated_at": {
        "type": "datetime"
    }
}