{
    "created_at": {
        "type": "datetime"
    },
    "created_by": {
        "type": "string"
    },
    "mathongso": {
        "length": null,
        "type": "string"
    },
    "updated_at": {
        "type": "datetime"
    },
    "baocaoapdung": {
        "type": ""
    },
    "id": {
        "primary": true,
        "type": "string"
    },
    "updated_by": {
        "type": "string"
    },
    "tenthongso": {
        "length": null,
        "type": "string"
    },
    "deleted_by": {
        "type": "string"
    },
    "deleted": {
        "type": "boolean"
    },
    "deleted_at": {
        "type": "datetime"
    }
}