{
    "created_at": {
        "type": "datetime"
    },
    "created_by": {
        "type": "string"
    },
    "updated_at": {
        "type": "datetime"
    },
    "updated_by": {
        "type": "string"
    },
    "deleted": {
        "type": "boolean"
    },
    "deleted_by": {
        "type": "string"
    },
    "deleted_at": {
        "type": "datetime"
    },
    "id": {
        "type": "string",
        "primary": true
    },
    "tenphuluc": {
        "type": "string",
        "length": null
    },
    "thongtu": {
        "type": "string",
        "length": null
    },
    "ngaybanhanhthongtu": {
        "type": "datetime"
    },
    "tenphieu": {
        "type": "string",
        "length": null
    },
    "donvibaocao": {
        "type": "string",
        "length": null
    },
    "phamvi": {
        "type": "string",
        "length": null
    },
    "ngaynaocao": {
        "type": "datetime"
    },
    "kqvschung_id": {
        "type": "string"
    },
    "tongsomaunuoclamxetnghiem": {
        "type": "string",
        "length": null
    },
    "tongsodat": {
        "type": "string",
        "length": null
    },
    "tyledat": {
        "type": "string",
        "length": null
    },
    "tongsokdat": {
        "type": "string",
        "length": null
    },
    "cumdancuduoi500ng_id": {
        "type": "string"
    },
    "cacbienphapsuly": {
        "type": "string",
        "length": null
    },
    "cacbienphapsuly500ng_id": {
        "type": "string"
    },
    "nhanxet": {
        "type": "string",
        "length": null
    },
    "kiennghi": {
        "type": "string",
        "length": null
    },
    "kyten": {
        "type": "string",
        "length": null
    },
    "kqvschung": {
        "type": "dict"
    },
    "cumdancuduoi500ng": {
        "type": "dict"
    },
    "cacbienphapsuly500ng": {
        "type": "dict"
    }
}